earnapp/__init__.py
earnapp/earnapp.py
earnapp-0.1.9.dist-info/COPYING
earnapp-0.1.9.dist-info/METADATA
earnapp-0.1.9.dist-info/WHEEL
earnapp-0.1.9.dist-info/top_level.txt
earnapp-0.1.9.dist-info/RECORD
