Metadata-Version: 2.1
Name: earnapp
Version: 0.1.9
Summary: A python library to interact with the EarnApp API
Home-page: https://github.com/Woodie-07/earnapp.py
Author: Woodie
Author-email: woodie@woodie.cf
License-File: COPYING
Requires-Dist: requests
